{"src/lib/components/BingMaps.react.js": {"description": "", "displayName": "BingMaps", "methods": [{"name": "afterDependencyLoad", "docblock": null, "modifiers": [], "params": [{"name": "pendingProps", "type": null}], "returns": null}, {"name": "loadScript", "docblock": null, "modifiers": [], "params": [{"name": "url", "type": null}], "returns": null}, {"name": "isColor", "docblock": null, "modifiers": [], "params": [{"name": "str", "type": null}], "returns": null}, {"name": "initMap", "docblock": null, "modifiers": [], "params": [{"name": "props", "type": null}, {"name": "Microsoft", "type": null}], "returns": null}, {"name": "setDirections", "docblock": null, "modifiers": [], "params": [{"name": "directions", "type": null}, {"name": "mapReference", "type": null}], "returns": null}, {"name": "setMapCenter", "docblock": null, "modifiers": [], "params": [{"name": "center", "type": null}, {"name": "mapReference", "type": null}], "returns": null}, {"name": "setMapNavigationBar", "docblock": null, "modifiers": [], "params": [{"name": "navigationBar", "type": null}, {"name": "mapReference", "type": null}], "returns": null}, {"name": "setMapTypeId", "docblock": null, "modifiers": [], "params": [{"name": "mapTypeId", "type": null}, {"name": "mapReference", "type": null}], "returns": null}, {"name": "setMapZoom", "docblock": null, "modifiers": [], "params": [{"name": "zoom", "type": null}, {"name": "mapReference", "type": null}], "returns": null}, {"name": "setPushpins", "docblock": null, "modifiers": [], "params": [{"name": "pushpins", "type": null}, {"name": "infoboxOptions", "type": null}, {"name": "mapReference", "type": null}, {"name": "setProps", "type": null}], "returns": null}, {"name": "setPolygons", "docblock": null, "modifiers": [], "params": [{"name": "polygons", "type": null}, {"name": "mapReference", "type": null}], "returns": null}, {"name": "setPolyline", "docblock": null, "modifiers": [], "params": [{"name": "polylines", "type": null}, {"name": "mapReference", "type": null}], "returns": null}], "props": {"bingKey": {"type": {"name": "union", "value": [{"name": "string"}, {"name": "number"}]}, "required": false, "description": "API Key for Bing Maps V8 Web Control", "defaultValue": {"value": "'AlXL42w92coK1623DVOrVzA1Gf-pUQbKb641JzTw_47B_sBpXowhGfvDbN6P70IE'", "computed": false}}, "center": {"type": {"name": "arrayOf", "value": {"name": "number"}}, "required": false, "description": "Array containing latitude and longitude of the map center", "defaultValue": {"value": "[48.800050, 9.797662]", "computed": false}}, "directions": {"type": {"name": "object"}, "required": false, "description": "Directions (needs better proptype protection)", "defaultValue": {"value": "undefined", "computed": true}}, "id": {"type": {"name": "string"}, "required": false, "description": "Id to which map DOM elements will be bound to as children", "defaultValue": {"value": "undefined", "computed": true}}, "infoboxOptions": {"type": {"name": "object"}, "required": false, "description": "infoboxOptions"}, "mapTypeId": {"type": {"name": "string"}, "required": false, "description": "Map type\r\nhttps://docs.microsoft.com/en-us/bingmaps/v8-web-control/map-control-api/maptypeid-enumeration", "defaultValue": {"value": "'canvasLight'", "computed": false}}, "navigationBar": {"type": {"name": "shape", "value": {"mode": {"name": "enum", "value": [{"value": "'compact'", "computed": false}, {"value": "'default'", "computed": false}, {"value": "'minified'", "computed": false}], "required": false}, "orientation": {"name": "enum", "value": [{"value": "'horizontal'", "computed": false}, {"value": "'vertical'", "computed": false}], "required": false}}}, "required": false, "description": "Navigation bar display configuration\r\nhttps://docs.microsoft.com/en-us/bingmaps/v8-web-control/map-control-api/navigationbarmode-enumeration", "defaultValue": {"value": "{\r\n    mode: 'minified',\r\n    orientation: 'horizontal'\r\n}", "computed": false}}, "polygons": {"type": {"name": "arrayOf", "value": {"name": "union", "value": [{"name": "shape", "value": {"method": {"name": "custom", "raw": "'simple'", "required": false}, "center": {"name": "arrayOf", "value": {"name": "number"}, "required": false}, "radius": {"name": "number", "required": false}, "points": {"name": "number", "required": false}, "options": {"name": "object", "required": false}}}, {"name": "shape", "value": {"method": {"name": "custom", "raw": "'complex'", "required": false}, "points": {"name": "arrayOf", "value": {"name": "arrayOf", "value": {"name": "number"}}, "required": false}, "options": {"name": "object", "required": false}}}]}}, "required": false, "description": "Polgons - either simple (creating points automatically) or complex (needs point input)", "defaultValue": {"value": "undefined", "computed": true}}, "polylines": {"type": {"name": "array"}, "required": false, "description": "Polylines from point A to B (needs better proptype protection)", "defaultValue": {"value": "undefined", "computed": true}}, "pushpins": {"type": {"name": "arrayOf", "value": {"name": "shape", "value": {"location": {"name": "arrayOf", "value": {"name": "number"}, "required": false}, "options": {"name": "object", "required": false}, "metadata": {"name": "object", "required": false}}}}, "required": false, "description": "Pushpins to be added to map", "defaultValue": {"value": "undefined", "computed": true}}, "setProps": {"type": {"name": "func"}, "required": false, "description": "Dash-assigned callback that informs the dash renderer that this component's\r\nproperties have changed"}, "selected": {"type": {"name": "string"}, "required": false, "description": "Id of selected object in component (only pushpins for now)", "defaultValue": {"value": "undefined", "computed": true}}, "zoom": {"type": {"name": "number"}, "required": false, "description": "Zoom level", "defaultValue": {"value": "14", "computed": false}}}}}